LICENSE
README.md
setup.py
pydoris/__init__.py
pydoris/doris_client.py
pydoris/selectdb/__init__.py
pydoris/selectdb/batch.py
pydoris/selectdb/config.py
pydoris/selectdb/db_operator.py
pydoris/selectdb/error.py
pydoris/selectdb/http_builder.py
pydoris/selectdb/selectdb_client.py
pydoris/selectdb/selectdb_utils.py
pydoris/selectdb/stage_load.py
pydoris/util/__init__.py
pydoris/util/generate_test_data.py
pydoris_client.egg-info/PKG-INFO
pydoris_client.egg-info/SOURCES.txt
pydoris_client.egg-info/dependency_links.txt
pydoris_client.egg-info/not-zip-safe
pydoris_client.egg-info/requires.txt
pydoris_client.egg-info/top_level.txt