Metadata-Version: 2.1
Name: pydoris-client
Version: 1.0.4
Summary: Python interface to Doris
Home-page: https://github.com/apache/doris
Author: liujiwen-up,bingquanzhao
Author-email: wen15580974595@163.com
License: Apache 2.0
Classifier: Development Status :: 5 - Production/Stable
Classifier: Environment :: Console
Classifier: Intended Audience :: Developers
Classifier: License :: OSI Approved :: Apache Software License
Classifier: Programming Language :: Python
Classifier: Programming Language :: Python :: 3
Classifier: Programming Language :: Python :: Implementation :: CPython
Classifier: Programming Language :: Python :: Implementation :: PyPy
Classifier: Topic :: Database :: Front-Ends
License-File: LICENSE
